dsbox/__init__.py
dsbox/dsbox_dev_setup.py
dsbox/generate-primitive-json.py
dsbox/datapostprocessing/__init__.py
dsbox/datapostprocessing/ensemble_voting.py
dsbox/datapostprocessing/horizontal_concat.py
dsbox/datapostprocessing/unfold.py
dsbox/datapostprocessing/vertical_concat.py
dsbox/datapreprocessing/__init__.py
dsbox/datapreprocessing/cleaner/IQRScaler.py
dsbox/datapreprocessing/cleaner/__init__.py
dsbox/datapreprocessing/cleaner/cleaning_featurizer.py
dsbox/datapreprocessing/cleaner/column_fold.py
dsbox/datapreprocessing/cleaner/config.py
dsbox/datapreprocessing/cleaner/data_profile.py
dsbox/datapreprocessing/cleaner/denormalize.py
dsbox/datapreprocessing/cleaner/discretizer.py
dsbox/datapreprocessing/cleaner/encoder.py
dsbox/datapreprocessing/cleaner/greedy.py
dsbox/datapreprocessing/cleaner/iterative_regression.py
dsbox/datapreprocessing/cleaner/knn.py
dsbox/datapreprocessing/cleaner/labler.py
dsbox/datapreprocessing/cleaner/mean.py
dsbox/datapreprocessing/cleaner/mice.py
dsbox/datapreprocessing/cleaner/missing_value_pred.py
dsbox/datapreprocessing/cleaner/splitter.py
dsbox/datapreprocessing/cleaner/to_numeric.py
dsbox/datapreprocessing/cleaner/unary_encoder.py
dsbox/datapreprocessing/cleaner/voter.py
dsbox/datapreprocessing/cleaner/data_sample/sample1.csv
dsbox/datapreprocessing/cleaner/data_sample/sample2.csv
dsbox/datapreprocessing/cleaner/dependencies/__init__.py
dsbox/datapreprocessing/cleaner/dependencies/category_detection.py
dsbox/datapreprocessing/cleaner/dependencies/constants.py
dsbox/datapreprocessing/cleaner/dependencies/date_extractor.py
dsbox/datapreprocessing/cleaner/dependencies/date_featurizer_org.py
dsbox/datapreprocessing/cleaner/dependencies/date_regex_generator.py
dsbox/datapreprocessing/cleaner/dependencies/dtype_detector.py
dsbox/datapreprocessing/cleaner/dependencies/feature_compute_hih.py
dsbox/datapreprocessing/cleaner/dependencies/feature_compute_lfh.py
dsbox/datapreprocessing/cleaner/dependencies/helper_funcs.py
dsbox_primitives-1.6.2.dist-info/METADATA
dsbox_primitives-1.6.2.dist-info/WHEEL
dsbox_primitives-1.6.2.dist-info/entry_points.txt
dsbox_primitives-1.6.2.dist-info/top_level.txt
dsbox_primitives-1.6.2.dist-info/RECORD
