Metadata-Version: 2.1
Name: dsbox-primitives
Version: 1.6.2
Summary: DSBox data processing primitives for both cleaning and featurizer
Home-page: https://gitlab.com/datadrivendiscovery/contrib/dsbox-primitives.git
Author: USC ISI
Maintainer: Ke-Thia Yao
Maintainer-email: kyao@isi.edu
License: MIT
Keywords: d3m_primitive
Platform: UNKNOWN
Requires-Python: >=3.6
Requires-Dist: Keras (==2.3.1)
Requires-Dist: d3m
Requires-Dist: d3m-common-primitives
Requires-Dist: dateparser
Requires-Dist: easydict
Requires-Dist: fancyimpute
Requires-Dist: frozendict
Requires-Dist: langdetect (>=1.0.7)
Requires-Dist: numpy
Requires-Dist: pandas
Requires-Dist: pmdarima (==1.8.1)
Requires-Dist: python-dateutil (>=2.5.2)
Requires-Dist: pytypes
Requires-Dist: scikit-image
Requires-Dist: scikit-learn
Requires-Dist: stopit (==1.1.2)
Requires-Dist: tensorflow
Requires-Dist: tzlocal
Provides-Extra: opencv
Requires-Dist: opencv-python (<4.5.58,>=4.1) ; extra == 'opencv'
Provides-Extra: opencv-headless
Requires-Dist: opencv-python-headless (<=4.5.4.58,>=4.1) ; extra == 'opencv-headless'
